freighter/__init__.py
freighter/constants.py
freighter/devkit_tools.py
freighter/doltools.py
freighter/hooks.py
freighter-0.2.4.dist-info/LICENSE
freighter-0.2.4.dist-info/METADATA
freighter-0.2.4.dist-info/WHEEL
freighter-0.2.4.dist-info/top_level.txt
freighter-0.2.4.dist-info/RECORD
