Metadata-Version: 2.1
Name: freighter
Version: 0.2.4
Summary: Kai's GameCube modding library enabling C/C++ code injection into .dol executables.
Home-page: https://github.com/kai13xd/Freighter
Author: Kai (@kai13xd)
Author-email: akaisekai13@gmail.com
License: MIT License
Project-URL: Issues, https://github.com/kai13xd/Freighter/issues
Platform: UNKNOWN
Classifier: Topic :: Games/Entertainment
Classifier: Topic :: Software Development :: Compilers
Classifier: Programming Language :: Python :: 3.9
Classifier: Programming Language :: C
Classifier: Programming Language :: C++
Classifier: License :: OSI Approved :: MIT License
Classifier: Environment :: Console
Classifier: Operating System :: Microsoft :: Windows
Requires-Python: >=3.10
License-File: LICENSE
Requires-Dist: colorama
Requires-Dist: dolreader
Requires-Dist: pyelftools
Requires-Dist: geckolibs
